sysml_code_generator_web_gui/application.py
sysml_code_generator_web_gui/examples/traffic_light.json
sysml_code_generator_web_gui/examples/traffic_light.sysml
sysml_code_generator_web_gui/public/css/bootstrap-theme.min.css
sysml_code_generator_web_gui/public/css/bootstrap-theme.min.css.map
sysml_code_generator_web_gui/public/css/bootstrap.min.css
sysml_code_generator_web_gui/public/css/bootstrap.min.css.map
sysml_code_generator_web_gui/public/traffic_light.json
sysml_code_generator_web_gui/templates/api.html
sysml_code_generator_web_gui/templates/example.html
sysml_code_generator_web_gui/templates/index.html
sysml_code_generator_web_gui/templates/navigation.html
sysml_code_generator_web_gui/templates/result.html
fcp89_sysml_v2_code_generator_web_gui-1.1.0.dist-info/entry_points.txt
fcp89_sysml_v2_code_generator_web_gui-1.1.0.dist-info/LICENSE
fcp89_sysml_v2_code_generator_web_gui-1.1.0.dist-info/METADATA
fcp89_sysml_v2_code_generator_web_gui-1.1.0.dist-info/WHEEL
fcp89_sysml_v2_code_generator_web_gui-1.1.0.dist-info/RECORD
