Metadata-Version: 2.1
Name: fcp89-sysml-v2-code-generator-web-gui
Version: 1.1.0
Summary: Web GUI for the SysML v2 code generator prototype.
Requires-Python: >=3.9
Classifier: Programming Language :: Python :: 3
Classifier: Programming Language :: Python :: 3.9
Classifier: Programming Language :: Python :: 3.10
Classifier: Programming Language :: Python :: 3.11
Classifier: Programming Language :: Python :: 3.12
Requires-Dist: fcp89-sysml-v2-code-generator (>=1.0.0,<2.0.0)
Requires-Dist: flask (>=3.1.0,<4.0.0)
